{
  "zoom": 14,
  "x": 9379,
  "y": 5935,
  "bounds": {
    "north": 44.35527821160296,
    "south": 44.33956524809713,
    "east": 26.103515625,
    "west": 26.08154296875
  },
  "center": {
    "lat": 44.34742172985004,
    "lng": 26.092529296875
  },
  "cellSize": 250,
  "cells": [
    {
      "lat": 44.351123,
      "lng": 26.083368,
      "distMetroM": 7179,
      "nearestMetro": "Tineretului",
      "poiCounts": {
        "schools": 0,
        "supermarkets": 0,
        "restaurants": 0,
        "parks": 0
      },
      "medianEurM2": null,
      "intelligenceScore": 0.05
    },
    {
      "lat": 44.351123,
      "lng": 26.086514,
      "distMetroM": 7122,
      "nearestMetro": "Tineretului",
      "poiCounts": {
        "schools": 0,
        "supermarkets": 0,
        "restaurants": 0,
        "parks": 0
      },
      "medianEurM2": null,
      "intelligenceScore": 0.05
    },
    {
      "lat": 44.351123,
      "lng": 26.08966,
      "distMetroM": 7073,
      "nearestMetro": "Tineretului",
      "poiCounts": {
        "schools": 0,
        "supermarkets": 0,
        "restaurants": 0,
        "parks": 0
      },
      "medianEurM2": null,
      "intelligenceScore": 0.05
    },
    {
      "lat": 44.351123,
      "lng": 26.092806,
      "distMetroM": 7032,
      "nearestMetro": "Tineretului",
      "poiCounts": {
        "schools": 0,
        "supermarkets": 0,
        "restaurants": 0,
        "parks": 0
      },
      "medianEurM2": null,
      "intelligenceScore": 0.05
    },
    {
      "lat": 44.351123,
      "lng": 26.095952,
      "distMetroM": 7000,
      "nearestMetro": "Tineretului",
      "poiCounts": {
        "schools": 0,
        "supermarkets": 0,
        "restaurants": 0,
        "parks": 0
      },
      "medianEurM2": null,
      "intelligenceScore": 0.05
    },
    {
      "lat": 44.351123,
      "lng": 26.099098,
      "distMetroM": 6977,
      "nearestMetro": "Tineretului",
      "poiCounts": {
        "schools": 0,
        "supermarkets": 0,
        "restaurants": 0,
        "parks": 0
      },
      "medianEurM2": null,
      "intelligenceScore": 0.05
    },
    {
      "lat": 44.351123,
      "lng": 26.102244,
      "distMetroM": 6963,
      "nearestMetro": "Tineretului",
      "poiCounts": {
        "schools": 0,
        "supermarkets": 0,
        "restaurants": 0,
        "parks": 0
      },
      "medianEurM2": null,
      "intelligenceScore": 0.05
    },
    {
      "lat": 44.353369,
      "lng": 26.083368,
      "distMetroM": 6937,
      "nearestMetro": "Tineretului",
      "poiCounts": {
        "schools": 0,
        "supermarkets": 0,
        "restaurants": 0,
        "parks": 0
      },
      "medianEurM2": null,
      "intelligenceScore": 0.05
    },
    {
      "lat": 44.353369,
      "lng": 26.086514,
      "distMetroM": 6878,
      "nearestMetro": "Tineretului",
      "poiCounts": {
        "schools": 0,
        "supermarkets": 0,
        "restaurants": 0,
        "parks": 0
      },
      "medianEurM2": null,
      "intelligenceScore": 0.05
    },
    {
      "lat": 44.353369,
      "lng": 26.08966,
      "distMetroM": 6827,
      "nearestMetro": "Tineretului",
      "poiCounts": {
        "schools": 0,
        "supermarkets": 0,
        "restaurants": 0,
        "parks": 0
      },
      "medianEurM2": null,
      "intelligenceScore": 0.05
    },
    {
      "lat": 44.353369,
      "lng": 26.092806,
      "distMetroM": 6785,
      "nearestMetro": "Tineretului",
      "poiCounts": {
        "schools": 0,
        "supermarkets": 0,
        "restaurants": 0,
        "parks": 0
      },
      "medianEurM2": null,
      "intelligenceScore": 0.05
    },
    {
      "lat": 44.353369,
      "lng": 26.095952,
      "distMetroM": 6752,
      "nearestMetro": "Tineretului",
      "poiCounts": {
        "schools": 0,
        "supermarkets": 0,
        "restaurants": 0,
        "parks": 0
      },
      "medianEurM2": null,
      "intelligenceScore": 0.05
    },
    {
      "lat": 44.353369,
      "lng": 26.099098,
      "distMetroM": 6728,
      "nearestMetro": "Tineretului",
      "poiCounts": {
        "schools": 0,
        "supermarkets": 0,
        "restaurants": 0,
        "parks": 0
      },
      "medianEurM2": null,
      "intelligenceScore": 0.05
    },
    {
      "lat": 44.353369,
      "lng": 26.102244,
      "distMetroM": 6714,
      "nearestMetro": "Tineretului",
      "poiCounts": {
        "schools": 0,
        "supermarkets": 0,
        "restaurants": 0,
        "parks": 0
      },
      "medianEurM2": null,
      "intelligenceScore": 0.05
    }
  ]
}